illyrian/__init__.py
illyrian/__main__.py
illyrian/cpython/__init__.py
illyrian/cpython/code.py
illyrian/cpython/cpython310.py
illyrian/cpython/cpython311.py
illyrian/cpython/cpython36.py
illyrian/cpython/cpython37.py
illyrian/cpython/cpython38.py
illyrian/cpython/cpython39.py
illyrian/env.py
illyrian/info.py
illyrian/manylinux/__init__.py
illyrian/manylinux/code.py
illyrian/run.py
illyrian/util/__init__.py
illyrian/util/code.py
illyrian/verify.py
illyrian/version.py
illyrian/wheel.py
illyrian/cmake/FindIllyrian.cmake
illyrian/cmake/illyrian.cmake
illyrian-0.3.7.dist-info/LICENSE
illyrian-0.3.7.dist-info/METADATA
illyrian-0.3.7.dist-info/top_list.txt
illyrian-0.3.7.dist-info/WHEEL
illyrian-0.3.7.dist-info/entry_points.txt
illyrian-0.3.7.dist-info/RECORD
