Metadata-Version: 2.1
Name: illyrian
Version: 0.3.7
Requires-Python: >=3.6
Summary: Illyrian is CMake extension for easily creating Python packages.
Author: Nicolas Weber
Author-email: nicolas.weber@neclab.eu
Classifier: License :: OSI Approved :: BSD License
Classifier: Programming Language :: Python :: 3 :: Only
Download-URL: https://github.com/nec-research/illyrian/tags
License: 3 BSD-License
Platform: linux_x86_x64
Requires-Dist: auditwheel
Requires-Dist: importlib-resources; python_version < "3.7"
Requires-Dist: pydot
